Metadata-Version: 1.1
Name: cmdperfect
Version: 0.2
Summary: Hy, this is cool librari for making cmd programs more beautifull and easy
Home-page: UNKNOWN
Author: UNKNOWN
Author-email: UNKNOWN
License: MIT
Keywords: cmd display perfect cmdperfect perfectcmd cool
Platform: UNKNOWN
Classifier: Development Status :: 5 - Production/Stable
Classifier: Intended Audience :: Education
Classifier: Operating System :: Microsoft :: Windows :: Windows 10
Classifier: Programming Language :: Python :: 3
